cube_simulator-2.3.7.dist-info/METADATA
cube_simulator-2.3.7.dist-info/RECORD
cube_simulator-2.3.7.dist-info/WHEEL
cube_simulator-2.3.7.dist-info/top_level.txt
simulator/__init__.py
simulator/constants.py
simulator/date_utils.py
simulator/flows.py
simulator/simulator.py
