Metadata-Version: 2.1
Name: cube-simulator
Version: 2.3.7
Summary: A money flow simuator
Home-page: http://github.com/CubeConsumerServivesPvtLtd/simulator
Author: Shashank Singh
Author-email: shashank.s.1903@gmail.com
License: MIT
Platform: UNKNOWN
Requires-Dist: python-dateutil
